Workbook

Sheet Inputs
A1: Inputs (yellow cells are editable). Tags: [A] assumption, [H] hypothesis, [E] estimate, [C] calculated, [ES] externally sourced, [SS] source-stated.
A2: Input | B2: Value | C2: Unit | D2: Tag | E2: Basis
A3: USD to INR exchange rate | B3: 88 | C3: INR per USD | D3: [A] | E3: Update monthly from RBI reference rate
A4: GST on Indian subscriptions | B4: 0.18 | C4: rate | D4: [A] | E4: Suno India prices include 18% GST (SRC-111); confirm with tax adviser (COMP-IN-07)
A5: Razorpay fee | B5: 0.02 | C5: share of charge | D5: [A] | E5: Confirm with Razorpay pricing (C-04)
A6: Merchant-of-record fee (percentage) | B6: 0.05 | C6: share of charge | D6: [A] | E6: Confirm with provider (ADR-009)
A7: Merchant-of-record fee (fixed) | B7: 0.5 | C7: USD per charge | D7: [A] | E7: Confirm with provider
A8: GPU cost per take, self-hosted | B8: 0.004 | C8: USD | D8: [C] | E8: TDD 9.1: 0.002 to 0.006 at 25% utilisation
A9: Lyria fallback cost per take | B9: 0.08 | C9: USD | D9: [ES] | E9: SRC-115
A10: Share of paid takes on fallback | B10: 0 | C10: share | D10: [H] | E10: Recommended 0% in India at launch; raise only if Hindi fails G1
A11: Storage and delivery per kept song per month | B11: 0.0005 | C11: USD | D11: [E] | E11: R2 free tier first (A-029)
A12: Free user takes per active month | B12: 20 | C12: takes | D12: [H] | E12: Daily caps limit this
A13: Paid usage as share of allowance | B13: 0.35 | C13: share | D13: [H] | E13: To measure in beta
A14: Monthly free-user churn | B14: 0.4 | C14: share | D14: [H]
A15: Monthly paid churn | B15: 0.08 | C15: share | D15: [H]
A16: Founders' monthly cash budget before funding | B16: 5000 | C16: INR | D16: [SS] | E16: DEC-023: ₹5,000 to ₹10,000; floor used

Sheet Plans
A1: Base prices (US band) and allowances [H]. Local prices are rounded price points; India shown in INR including GST.
A2: Plan | B2: Base US price (USD/month) | C2: Takes allowance per month | D2: Tag
A3: Creator | B3: 8 | C3: 300 | D3: [H]
A4: Pro | B4: 18 | C4: 800 | D4: [H]
A6: Band | B6: Factor | C6: Example countries | D6: Creator (USD equiv.) | E6: Pro (USD equiv.)
A7: B1 | B7: 1 | C7: US, UK, EU, Australia, Japan | D7: =$B$3*B7 | E7: =$B$4*B7
A8: B2 | B8: 0.6 | C8: Mexico, South Korea, Gulf | D8: =$B$3*B8 | E8: =$B$4*B8
A9: B3 | B9: 0.35 | C9: Brazil, Indonesia | D9: =$B$3*B9 | E9: =$B$4*B9
A10: B4 | B10: 0.2 | C10: India, Philippines, Nepal, Turkey | D10: =$B$3*B10 | E10: =$B$4*B10
A11: B5 | B11: 0.12 | C11: Pakistan, Bangladesh, Egypt, Nigeria | D11: =$B$3*B11 | E11: =$B$4*B11
A13: India price points (INR incl. GST) | B13: Creator | C13: Pro | D13: Basis
A14: Formula price (band B4 x base x FX) | B14: =D10*Inputs!$B$3 | C14: =E10*Inputs!$B$3 | D14: [C]
A15: Chosen price point | B15: 149 | C15: 349 | D15: [H] Rounded; Spotify India ₹199 (SRC-116); Suno Pro India ₹999 (SRC-111)

Sheet Unit economics
A1: Contribution per paying user per month (USD). India uses Razorpay and GST-inclusive prices; band B1 uses a merchant of record with tax added on top.
A2: Line | B2: India Creator | C2: India Pro | D2: B1 Creator | E2: B1 Pro
A3: List price (local) | B3: =Plans!B15 | C3: =Plans!C15 | D3: =Plans!D7 | E3: =Plans!E7
A4: Net of GST (USD) | B4: =B3/(1+Inputs!$B$4)/Inputs!$B$3 | C4: =C3/(1+Inputs!$B$4)/Inputs!$B$3 | D4: =D3 | E4: =E3
A5: Payment fees (USD) | B5: =B4*Inputs!$B$5 | C5: =C4*Inputs!$B$5 | D5: =D4*Inputs!$B$6+Inputs!$B$7 | E5: =E4*Inputs!$B$6+Inputs!$B$7
A6: Net revenue (USD) | B6: =B4-B5 | C6: =C4-C5 | D6: =D4-D5 | E6: =E4-E5
A7: Takes used | B7: =Plans!$C$3*Inputs!$B$13 | C7: =Plans!$C$4*Inputs!$B$13 | D7: =Plans!$C$3*Inputs!$B$13 | E7: =Plans!$C$4*Inputs!$B$13
A8: Cost per take (USD) | B8: =(1-Inputs!$B$10)*Inputs!$B$8+Inputs!$B$10*Inputs!$B$9 | C8: =B8 | D8: =B8 | E8: =B8
A9: Compute cost (USD) | B9: =B7*B8 | C9: =C7*C8 | D9: =D7*D8 | E9: =E7*E8
A10: Storage and delivery (USD) | B10: =B7*0.2*Inputs!$B$11*12 | C10: =C7*0.2*Inputs!$B$11*12 | D10: =D7*0.2*Inputs!$B$11*12 | E10: =E7*0.2*Inputs!$B$11*12
A11: Contribution (USD) | B11: =B6-B9-B10 | C11: =C6-C9-C10 | D11: =D6-D9-D10 | E11: =E6-E9-E10
A12: Contribution margin | B12: =B11/B6 | C12: =C11/C6 | D12: =D11/D6 | E12: =E11/E6
A13: Break-even fallback share | B13: =(B6-B10-B7*Inputs!$B$8)/(B7*(Inputs!$B$9-Inputs!$B$8)) | C13: =(C6-C10-C7*Inputs!$B$8)/(C7*(Inputs!$B$9-Inputs!$B$8)) | D13: =(D6-D10-D7*Inputs!$B$8)/(D7*(Inputs!$B$9-Inputs!$B$8)) | E13: =(E6-E10-E7*Inputs!$B$8)/(E7*(Inputs!$B$9-Inputs!$B$8))
A14: Free user cost per active month (USD) | B14: =Inputs!$B$12*Inputs!$B$8
A15: Storage line assumes 20% of takes are kept and stored for 12 months [H].

Sheet Scenarios
A1: 12-month scenarios from beta start. These are hypotheses for planning, not forecasts or traction. Edit row 4 to 7.
A3: Scenario input | B3: Low | C3: Base | D3: High | E3: Tag
A4: New free sign-ups in month 1 | B4: 500 | C4: 2000 | D4: 6000 | E4: [H]
A5: Monthly growth in new sign-ups | B5: 0.05 | C5: 0.15 | D5: 0.25 | E5: [H]
A6: Free-to-paid conversion per month of active free users | B6: 0.01 | C6: 0.025 | D6: 0.05 | E6: [H]
A7: Share of paid users on Pro (rest Creator) | B7: 0.2 | C7: 0.3 | D7: 0.4 | E7: [H]
A10: Low scenario (India price points)
A11: Metric | B11: M1 | C11: M2 | D11: M3 | E11: M4 | F11: M5 | G11: M6 | H11: M7 | I11: M8 | J11: M9 | K11: M10 | L11: M11 | M11: M12
A12: New free sign-ups | B12: =$B$4*(1+$B$5)^0 | C12: =$B$4*(1+$B$5)^1 | D12: =$B$4*(1+$B$5)^2 | E12: =$B$4*(1+$B$5)^3 | F12: =$B$4*(1+$B$5)^4 | G12: =$B$4*(1+$B$5)^5 | H12: =$B$4*(1+$B$5)^6 | I12: =$B$4*(1+$B$5)^7 | J12: =$B$4*(1+$B$5)^8 | K12: =$B$4*(1+$B$5)^9 | L12: =$B$4*(1+$B$5)^10 | M12: =$B$4*(1+$B$5)^11
A13: Active free users | B13: =B12 | C13: =B13*(1-Inputs!$B$14)+C12 | D13: =C13*(1-Inputs!$B$14)+D12 | E13: =D13*(1-Inputs!$B$14)+E12 | F13: =E13*(1-Inputs!$B$14)+F12 | G13: =F13*(1-Inputs!$B$14)+G12 | H13: =G13*(1-Inputs!$B$14)+H12 | I13: =H13*(1-Inputs!$B$14)+I12 | J13: =I13*(1-Inputs!$B$14)+J12 | ... M13: =L13*(1-Inputs!$B$14)+M12
A14: New paid users | B14: =B13*$B$6 | C14: =C13*$B$6 | D14: =D13*$B$6 | E14: =E13*$B$6 | F14: =F13*$B$6 | G14: =G13*$B$6 | H14: =H13*$B$6 | I14: =I13*$B$6 | ... M14: =M13*$B$6
A15: Active paid users | B15: =B14 | C15: =B15*(1-Inputs!$B$15)+C14 | D15: =C15*(1-Inputs!$B$15)+D14 | E15: =D15*(1-Inputs!$B$15)+E14 | F15: =E15*(1-Inputs!$B$15)+F14 | G15: =F15*(1-Inputs!$B$15)+G14 | H15: =G15*(1-Inputs!$B$15)+H14 | I15: =H15*(1-Inputs!$B$15)+I14 | J15: =I15*(1-Inputs!$B$15)+J14 | ... M15: =L15*(1-Inputs!$B$15)+M14
A16: Net revenue (USD) | B16: =B15*((1-$B$7)*'Unit economics'!$B$6+$B$7*'Unit economics'!$C$6) | C16: =C15*((1-$B$7)*'Unit economics'!$B$6+$B$7*'Unit economics'!$C$6) | D16: =D15*((1-$B$7)*'Unit economics'!$B$6+$B$7*'Unit economics'!$C$6) | E16: =E15*((1-$B$7)*'Unit economics'!$B$6+$B$7*'Unit economics'!$C$6) | F16: =F15*((1-$B$7)*'Unit economics'!$B$6+$B$7*'Unit economics'!$C$6) | G16: =G15*((1-$B$7)*'Unit economics'!$B$6+$B$7*'Unit economics'!$C$6) | H16: =H15*((1-$B$7)*'Unit economics'!$B$6+$B$7*'Unit economics'!$C$6) | I16: =I15*((1-$B$7)*'Unit economics'!$B$6+$B$7*'Unit economics'!$C$6) | ... M16: =M15*((1-$B$7)*'Unit economics'!$B$6+$B$7*'Unit economics'!$C$6)
A17: Paid compute and storage (USD) | B17: =B15*((1-$B$7)*('Unit economics'!$B$9+'Unit economics'!$B$10)+$B$7*('Unit economics'!$C$9+'Unit economics'!$C$10)) | C17: =C15*((1-$B$7)*('Unit economics'!$B$9+'Unit economics'!$B$10)+$B$7*('Unit economics'!$C$9+'Unit economics'!$C$10)) | D17: =D15*((1-$B$7)*('Unit economics'!$B$9+'Unit economics'!$B$10)+$B$7*('Unit economics'!$C$9+'Unit economics'!$C$10)) | E17: =E15*((1-$B$7)*('Unit economics'!$B$9+'Unit economics'!$B$10)+$B$7*('Unit economics'!$C$9+'Unit economics'!$C$10)) | F17: =F15*((1-$B$7)*('Unit economics'!$B$9+'Unit economics'!$B$10)+$B$7*('Unit economics'!$C$9+'Unit economics'!$C$10)) | G17: =G15*((1-$B$7)*('Unit economics'!$B$9+'Unit economics'!$B$10)+$B$7*('Unit economics'!$C$9+'Unit economics'!$C$10)) | H17: =H15*((1-$B$7)*('Unit economics'!$B$9+'Unit economics'!$B$10)+$B$7*('Unit economics'!$C$9+'Unit economics'!$C$10)) | I17: =I15*((1-$B$7)*('Unit economics'!$B$9+'Unit economics'!$B$10)+$B$7*('Unit economics'!$C$9+'Unit economics'!$C$10)) | ... M17: =M15*((1-$B$7)*('Unit economics'!$B$9+'Unit economics'!$B$10)+$B$7*('Unit economics'!$C$9+'Unit economics'!$C$10))
A18: Free-tier compute (USD) | B18: =B13*'Unit economics'!$B$14 | C18: =C13*'Unit economics'!$B$14 | D18: =D13*'Unit economics'!$B$14 | E18: =E13*'Unit economics'!$B$14 | F18: =F13*'Unit economics'!$B$14 | G18: =G13*'Unit economics'!$B$14 | H18: =H13*'Unit economics'!$B$14 | I18: =I13*'Unit economics'!$B$14 | ... M18: =M13*'Unit economics'!$B$14
A19: Contribution after free-tier cost (USD) | B19: =B16-B17-B18 | C19: =C16-C17-C18 | D19: =D16-D17-D18 | E19: =E16-E17-E18 | F19: =F16-F17-F18 | G19: =G16-G17-G18 | H19: =H16-H17-H18 | I19: =I16-I17-I18 | ... M19: =M16-M17-M18
A20: Cumulative contribution (USD) | B20: =B19 | C20: =B20+C19 | D20: =C20+D19 | E20: =D20+E19 | F20: =E20+F19 | G20: =F20+G19 | H20: =G20+H19 | I20: =H20+I19 | J20: =I20+J19 | ... M20: =L20+M19
A27: Base scenario (India price points)
A28: Metric | B28: M1 | C28: M2 | D28: M3 | E28: M4 | F28: M5 | G28: M6 | H28: M7 | I28: M8 | J28: M9 | K28: M10 | L28: M11 | M28: M12
A29: New free sign-ups | B29: =$C$4*(1+$C$5)^0 | C29: =$C$4*(1+$C$5)^1 | D29: =$C$4*(1+$C$5)^2 | E29: =$C$4*(1+$C$5)^3 | F29: =$C$4*(1+$C$5)^4 | G29: =$C$4*(1+$C$5)^5 | H29: =$C$4*(1+$C$5)^6 | I29: =$C$4*(1+$C$5)^7 | J29: =$C$4*(1+$C$5)^8 | K29: =$C$4*(1+$C$5)^9 | L29: =$C$4*(1+$C$5)^10 | M29: =$C$4*(1+$C$5)^11
A30: Active free users | B30: =B29 | C30: =B30*(1-Inputs!$B$14)+C29 | D30: =C30*(1-Inputs!$B$14)+D29 | E30: =D30*(1-Inputs!$B$14)+E29 | F30: =E30*(1-Inputs!$B$14)+F29 | G30: =F30*(1-Inputs!$B$14)+G29 | H30: =G30*(1-Inputs!$B$14)+H29 | I30: =H30*(1-Inputs!$B$14)+I29 | J30: =I30*(1-Inputs!$B$14)+J29 | ... M30: =L30*(1-Inputs!$B$14)+M29
A31: New paid users | B31: =B30*$C$6 | C31: =C30*$C$6 | D31: =D30*$C$6 | E31: =E30*$C$6 | F31: =F30*$C$6 | G31: =G30*$C$6 | H31: =H30*$C$6 | I31: =I30*$C$6 | ... M31: =M30*$C$6
A32: Active paid users | B32: =B31 | C32: =B32*(1-Inputs!$B$15)+C31 | D32: =C32*(1-Inputs!$B$15)+D31 | E32: =D32*(1-Inputs!$B$15)+E31 | F32: =E32*(1-Inputs!$B$15)+F31 | G32: =F32*(1-Inputs!$B$15)+G31 | H32: =G32*(1-Inputs!$B$15)+H31 | I32: =H32*(1-Inputs!$B$15)+I31 | J32: =I32*(1-Inputs!$B$15)+J31 | ... M32: =L32*(1-Inputs!$B$15)+M31
A33: Net revenue (USD) | B33: =B32*((1-$C$7)*'Unit economics'!$B$6+$C$7*'Unit economics'!$C$6) | C33: =C32*((1-$C$7)*'Unit economics'!$B$6+$C$7*'Unit economics'!$C$6) | D33: =D32*((1-$C$7)*'Unit economics'!$B$6+$C$7*'Unit economics'!$C$6) | E33: =E32*((1-$C$7)*'Unit economics'!$B$6+$C$7*'Unit economics'!$C$6) | F33: =F32*((1-$C$7)*'Unit economics'!$B$6+$C$7*'Unit economics'!$C$6) | G33: =G32*((1-$C$7)*'Unit economics'!$B$6+$C$7*'Unit economics'!$C$6) | H33: =H32*((1-$C$7)*'Unit economics'!$B$6+$C$7*'Unit economics'!$C$6) | I33: =I32*((1-$C$7)*'Unit economics'!$B$6+$C$7*'Unit economics'!$C$6) | ... M33: =M32*((1-$C$7)*'Unit economics'!$B$6+$C$7*'Unit economics'!$C$6)
A34: Paid compute and storage (USD) | B34: =B32*((1-$C$7)*('Unit economics'!$B$9+'Unit economics'!$B$10)+$C$7*('Unit economics'!$C$9+'Unit economics'!$C$10)) | C34: =C32*((1-$C$7)*('Unit economics'!$B$9+'Unit economics'!$B$10)+$C$7*('Unit economics'!$C$9+'Unit economics'!$C$10)) | D34: =D32*((1-$C$7)*('Unit economics'!$B$9+'Unit economics'!$B$10)+$C$7*('Unit economics'!$C$9+'Unit economics'!$C$10)) | E34: =E32*((1-$C$7)*('Unit economics'!$B$9+'Unit economics'!$B$10)+$C$7*('Unit economics'!$C$9+'Unit economics'!$C$10)) | F34: =F32*((1-$C$7)*('Unit economics'!$B$9+'Unit economics'!$B$10)+$C$7*('Unit economics'!$C$9+'Unit economics'!$C$10)) | G34: =G32*((1-$C$7)*('Unit economics'!$B$9+'Unit economics'!$B$10)+$C$7*('Unit economics'!$C$9+'Unit economics'!$C$10)) | H34: =H32*((1-$C$7)*('Unit economics'!$B$9+'Unit economics'!$B$10)+$C$7*('Unit economics'!$C$9+'Unit economics'!$C$10)) | I34: =I32*((1-$C$7)*('Unit economics'!$B$9+'Unit economics'!$B$10)+$C$7*('Unit economics'!$C$9+'Unit economics'!$C$10)) | ... M34: =M32*((1-$C$7)*('Unit economics'!$B$9+'Unit economics'!$B$10)+$C$7*('Unit economics'!$C$9+'Unit economics'!$C$10))
A35: Free-tier compute (USD) | B35: =B30*'Unit economics'!$B$14 | C35: =C30*'Unit economics'!$B$14 | D35: =D30*'Unit economics'!$B$14 | E35: =E30*'Unit economics'!$B$14 | F35: =F30*'Unit economics'!$B$14 | G35: =G30*'Unit economics'!$B$14 | H35: =H30*'Unit economics'!$B$14 | I35: =I30*'Unit economics'!$B$14 | ... M35: =M30*'Unit economics'!$B$14
A36: Contribution after free-tier cost (USD) | B36: =B33-B34-B35 | C36: =C33-C34-C35 | D36: =D33-D34-D35 | E36: =E33-E34-E35 | F36: =F33-F34-F35 | G36: =G33-G34-G35 | H36: =H33-H34-H35 | I36: =I33-I34-I35 | ... M36: =M33-M34-M35
A37: Cumulative contribution (USD) | B37: =B36 | C37: =B37+C36 | D37: =C37+D36 | E37: =D37+E36 | F37: =E37+F36 | G37: =F37+G36 | H37: =G37+H36 | I37: =H37+I36 | J37: =I37+J36 | ... M37: =L37+M36
A44: High scenario (India price points)
A45: Metric | B45: M1 | C45: M2 | D45: M3 | E45: M4 | F45: M5 | G45: M6 | H45: M7 | I45: M8 | J45: M9 | K45: M10 | L45: M11 | M45: M12
A46: New free sign-ups | B46: =$D$4*(1+$D$5)^0 | C46: =$D$4*(1+$D$5)^1 | D46: =$D$4*(1+$D$5)^2 | E46: =$D$4*(1+$D$5)^3 | F46: =$D$4*(1+$D$5)^4 | G46: =$D$4*(1+$D$5)^5 | H46: =$D$4*(1+$D$5)^6 | I46: =$D$4*(1+$D$5)^7 | J46: =$D$4*(1+$D$5)^8 | K46: =$D$4*(1+$D$5)^9 | L46: =$D$4*(1+$D$5)^10 | M46: =$D$4*(1+$D$5)^11
A47: Active free users | B47: =B46 | C47: =B47*(1-Inputs!$B$14)+C46 | D47: =C47*(1-Inputs!$B$14)+D46 | E47: =D47*(1-Inputs!$B$14)+E46 | F47: =E47*(1-Inputs!$B$14)+F46 | G47: =F47*(1-Inputs!$B$14)+G46 | H47: =G47*(1-Inputs!$B$14)+H46 | I47: =H47*(1-Inputs!$B$14)+I46 | J47: =I47*(1-Inputs!$B$14)+J46 | ... M47: =L47*(1-Inputs!$B$14)+M46
A48: New paid users | B48: =B47*$D$6 | C48: =C47*$D$6 | D48: =D47*$D$6 | E48: =E47*$D$6 | F48: =F47*$D$6 | G48: =G47*$D$6 | H48: =H47*$D$6 | I48: =I47*$D$6 | ... M48: =M47*$D$6
A49: Active paid users | B49: =B48 | C49: =B49*(1-Inputs!$B$15)+C48 | D49: =C49*(1-Inputs!$B$15)+D48 | E49: =D49*(1-Inputs!$B$15)+E48 | F49: =E49*(1-Inputs!$B$15)+F48 | G49: =F49*(1-Inputs!$B$15)+G48 | H49: =G49*(1-Inputs!$B$15)+H48 | I49: =H49*(1-Inputs!$B$15)+I48 | J49: =I49*(1-Inputs!$B$15)+J48 | ... M49: =L49*(1-Inputs!$B$15)+M48
A50: Net revenue (USD) | B50: =B49*((1-$D$7)*'Unit economics'!$B$6+$D$7*'Unit economics'!$C$6) | C50: =C49*((1-$D$7)*'Unit economics'!$B$6+$D$7*'Unit economics'!$C$6) | D50: =D49*((1-$D$7)*'Unit economics'!$B$6+$D$7*'Unit economics'!$C$6) | E50: =E49*((1-$D$7)*'Unit economics'!$B$6+$D$7*'Unit economics'!$C$6) | F50: =F49*((1-$D$7)*'Unit economics'!$B$6+$D$7*'Unit economics'!$C$6) | G50: =G49*((1-$D$7)*'Unit economics'!$B$6+$D$7*'Unit economics'!$C$6) | H50: =H49*((1-$D$7)*'Unit economics'!$B$6+$D$7*'Unit economics'!$C$6) | I50: =I49*((1-$D$7)*'Unit economics'!$B$6+$D$7*'Unit economics'!$C$6) | ... M50: =M49*((1-$D$7)*'Unit economics'!$B$6+$D$7*'Unit economics'!$C$6)
A51: Paid compute and storage (USD) | B51: =B49*((1-$D$7)*('Unit economics'!$B$9+'Unit economics'!$B$10)+$D$7*('Unit economics'!$C$9+'Unit economics'!$C$10)) | C51: =C49*((1-$D$7)*('Unit economics'!$B$9+'Unit economics'!$B$10)+$D$7*('Unit economics'!$C$9+'Unit economics'!$C$10)) | D51: =D49*((1-$D$7)*('Unit economics'!$B$9+'Unit economics'!$B$10)+$D$7*('Unit economics'!$C$9+'Unit economics'!$C$10)) | E51: =E49*((1-$D$7)*('Unit economics'!$B$9+'Unit economics'!$B$10)+$D$7*('Unit economics'!$C$9+'Unit economics'!$C$10)) | F51: =F49*((1-$D$7)*('Unit economics'!$B$9+'Unit economics'!$B$10)+$D$7*('Unit economics'!$C$9+'Unit economics'!$C$10)) | G51: =G49*((1-$D$7)*('Unit economics'!$B$9+'Unit economics'!$B$10)+$D$7*('Unit economics'!$C$9+'Unit economics'!$C$10)) | H51: =H49*((1-$D$7)*('Unit economics'!$B$9+'Unit economics'!$B$10)+$D$7*('Unit economics'!$C$9+'Unit economics'!$C$10)) | I51: =I49*((1-$D$7)*('Unit economics'!$B$9+'Unit economics'!$B$10)+$D$7*('Unit economics'!$C$9+'Unit economics'!$C$10)) | ... M51: =M49*((1-$D$7)*('Unit economics'!$B$9+'Unit economics'!$B$10)+$D$7*('Unit economics'!$C$9+'Unit economics'!$C$10))
A52: Free-tier compute (USD) | B52: =B47*'Unit economics'!$B$14 | C52: =C47*'Unit economics'!$B$14 | D52: =D47*'Unit economics'!$B$14 | E52: =E47*'Unit economics'!$B$14 | F52: =F47*'Unit economics'!$B$14 | G52: =G47*'Unit economics'!$B$14 | H52: =H47*'Unit economics'!$B$14 | I52: =I47*'Unit economics'!$B$14 | ... M52: =M47*'Unit economics'!$B$14
A53: Contribution after free-tier cost (USD) | B53: =B50-B51-B52 | C53: =C50-C51-C52 | D53: =D50-D51-D52 | E53: =E50-E51-E52 | F53: =F50-F51-F52 | G53: =G50-G51-G52 | H53: =H50-H51-H52 | I53: =I50-I51-I52 | ... M53: =M50-M51-M52
A54: Cumulative contribution (USD) | B54: =B53 | C54: =B54+C53 | D54: =C54+D53 | E54: =D54+E53 | F54: =E54+F53 | G54: =F54+G53 | H54: =G54+H53 | I54: =H54+I53 | J54: =I54+J53 | ... M54: =L54+M53

Sheet Budgets
A1: Recommended allocation of money. Shares are recommendations [E]; amounts follow the founders' decision (Q-F02) and any future round. No round size is assumed.
A3: Pre-funding monthly budget (DEC-023) | B3: ₹5,000 | C3: ₹10,000 | E3: Notes
A4: GPU compute for beta (rented, scale to zero) | B4: 0.6 | C4: 0.6 | E4: Largest variable cost; credits first
A5: Domain, email, tools beyond free tiers | B5: 0.1 | C5: 0.1
A6: Listening-test honoraria and interview incentives | B6: 0.1 | C6: 0.15 | E6: Evidence for investors
A7: Company compliance (accountant, filings) | B7: 0.2 | C7: 0.15 | E7: Needs quotes
A8: Counsel review of terms | B8: 0 | C8: 0 | E8: Pay one-off from savings before paid launch
A9: Total share | B9: =SUM(B4:B8) | C9: =SUM(C4:C8)
A11: Use of funds after a seed round (share) | B11: Share | C11: What it buys
A12: Product and engineering (hires, contractors) | B12: 0.4 | C12: Audio-ML engineer, second backend engineer, designer
A13: Compute (GPU inference, evaluation) | B13: 0.2 | C13: Lower latency, higher free caps, paid-cloud migration
A14: Licensed data and rights | B14: 0.15 | C14: Regional catalogue and commissioned sessions to retire RISK-001
A15: Go-to-market | B15: 0.15 | C15: Creator partnerships, content, paid tests in India
A16: Legal, compliance, finance and contingency | B16: 0.1 | C16: Counsel, audits, insurance, buffer
A17: Total share | B17: =SUM(B12:B16)
